odoo/addons/pricelist_cache_rest/README.rst
odoo/addons/pricelist_cache_rest/__init__.py
odoo/addons/pricelist_cache_rest/__manifest__.py
odoo/addons/pricelist_cache_rest/controllers/__init__.py
odoo/addons/pricelist_cache_rest/controllers/main.py
odoo/addons/pricelist_cache_rest/data/ir_exports_data.xml
odoo/addons/pricelist_cache_rest/demo/auth_api_key_demo.xml
odoo/addons/pricelist_cache_rest/i18n/es.po
odoo/addons/pricelist_cache_rest/i18n/it.po
odoo/addons/pricelist_cache_rest/i18n/pricelist_cache_rest.pot
odoo/addons/pricelist_cache_rest/models/__init__.py
odoo/addons/pricelist_cache_rest/models/res_company.py
odoo/addons/pricelist_cache_rest/models/res_config_settings.py
odoo/addons/pricelist_cache_rest/readme/CONFIGURATION.rst
odoo/addons/pricelist_cache_rest/readme/CONTRIBUTORS.md
odoo/addons/pricelist_cache_rest/readme/CREDITS.md
odoo/addons/pricelist_cache_rest/readme/DESCRIPTION.md
odoo/addons/pricelist_cache_rest/readme/USAGE.md
odoo/addons/pricelist_cache_rest/static/description/icon.png
odoo/addons/pricelist_cache_rest/static/description/index.html
odoo/addons/pricelist_cache_rest/tests/__init__.py
odoo/addons/pricelist_cache_rest/tests/test_pricelist_cache_rest.py
odoo/addons/pricelist_cache_rest/wizards/res_config_settings.xml
odoo_addon_pricelist_cache_rest-18.0.1.0.0.2.dist-info/METADATA
odoo_addon_pricelist_cache_rest-18.0.1.0.0.2.dist-info/WHEEL
odoo_addon_pricelist_cache_rest-18.0.1.0.0.2.dist-info/top_level.txt
odoo_addon_pricelist_cache_rest-18.0.1.0.0.2.dist-info/RECORD
