Metadata-Version: 2.1
Name: odoo-addon-pricelist_cache_rest
Version: 18.0.1.0.0.2
Requires-Python: >=3.10
Requires-Dist: odoo-addon-auth_api_key==18.0.*
Requires-Dist: odoo-addon-jsonifier==18.0.*
Requires-Dist: odoo-addon-pricelist_cache==18.0.*
Requires-Dist: odoo==18.0.*
Summary: Provides an endpoint to get product prices for a given customer
Home-page: https://github.com/OCA/sale-workflow
License: AGPL-3
Author: Odoo Community Association (OCA), Camptocamp
Author-email: support@odoo-community.org
Classifier: Programming Language :: Python
Classifier: Framework :: Odoo
Classifier: Framework :: Odoo :: 18.0
Classifier: License :: OSI Approved :: GNU Affero General Public License v3
